setup.py
dsnd_prob1/Binomialdistribution.py
dsnd_prob1/Gaussiandistribution.py
dsnd_prob1/Generaldistribution.py
dsnd_prob1/__init__.py
dsnd_prob1.egg-info/PKG-INFO
dsnd_prob1.egg-info/SOURCES.txt
dsnd_prob1.egg-info/dependency_links.txt
dsnd_prob1.egg-info/not-zip-safe
dsnd_prob1.egg-info/top_level.txt