Metadata-Version: 1.0
Name: dsnd-prob1
Version: 1.2
Summary: Gaussian and Binomial distributions
Home-page: UNKNOWN
Author: Vikas Sharma
Author-email: master2vikas@gmail.com
License: UNKNOWN
Platform: UNKNOWN
